yaqd_acton/VERSION
yaqd_acton/__init__.py
yaqd_acton/__version__.py
yaqd_acton/_acton_2150i.py
yaqd_acton/_acton_sp2300i.py
yaqd_acton/_actonmono.py
yaqd_acton/acton-2150i.avpr
yaqd_acton/acton-2150i.toml
yaqd_acton/acton-sp2300i.avpr
yaqd_acton/acton-sp2300i.toml
yaqd_acton-2023.9.0.dist-info/entry_points.txt
yaqd_acton-2023.9.0.dist-info/LICENSE
yaqd_acton-2023.9.0.dist-info/WHEEL
yaqd_acton-2023.9.0.dist-info/METADATA
yaqd_acton-2023.9.0.dist-info/RECORD
