Metadata-Version: 2.1
Name: yaqd-acton
Version: 2023.9.0
Summary: yaq daemons for Acton Research Corporation instruments
Home-page: https://github.com/yaq-project/yaqd-acton
Author: yaq developers
Requires-Python: >3.7
Classifier: Development Status :: 2 - Pre-Alpha
Classifier: Intended Audience :: Science/Research
Classifier: License :: OSI Approved :: GNU Lesser General Public License v3 (LGPLv3)
Classifier: Natural Language :: English
Classifier: Programming Language :: Python :: 3
Classifier: Programming Language :: Python :: 3.7
Classifier: Programming Language :: Python :: 3.8
Classifier: Topic :: Scientific/Engineering
Requires-Dist: yaqd-core>=2020.06.2
Requires-Dist: pyserial
Requires-Dist: black ; extra == "dev"
Requires-Dist: pre-commit ; extra == "dev"
Provides-Extra: dev
